dingtalker.py
dingtalker-0.0.6.dist-info/METADATA
dingtalker-0.0.6.dist-info/WHEEL
dingtalker-0.0.6.dist-info/entry_points.txt
dingtalker-0.0.6.dist-info/top_level.txt
dingtalker-0.0.6.dist-info/RECORD
