Metadata-Version: 2.1
Name: dingtalker
Version: 0.0.6
Summary: 钉钉机器人客户端工具。
Home-page: https://github.com/kancyframework/python-plugins/tree/main/dingtalker
Author: kancy
Author-email: 793272861@qq.com
License: MIT
Platform: UNKNOWN
Classifier: License :: OSI Approved :: MIT License
Classifier: Programming Language :: Python
Classifier: Programming Language :: Python :: 3
Classifier: Programming Language :: Python :: 3.6
Classifier: Programming Language :: Python :: Implementation :: CPython
Classifier: Programming Language :: Python :: Implementation :: PyPy
Requires-Python: >=3
Requires-Dist: requests
Provides-Extra: dingtalker_client_manager_feature
Requires-Dist: confer ; extra == 'dingtalker_client_manager_feature'
